ngsphy/__init__.py
ngsphy/__main__.py
ngsphy/coverage.py
ngsphy/individual.py
ngsphy/loggingformatter.py
ngsphy/msatools.py
ngsphy/ngsphy.py
ngsphy/ngsphyexceptions.py
ngsphy/readcounts.py
ngsphy/reads.py
ngsphy/rerooter.py
ngsphy/sequence.py
ngsphy/settings.py
ngsphy-1.0.13.data/scripts/ngsphy
ngsphy-1.0.13.dist-info/DESCRIPTION.rst
ngsphy-1.0.13.dist-info/LICENSE.txt
ngsphy-1.0.13.dist-info/METADATA
ngsphy-1.0.13.dist-info/RECORD
ngsphy-1.0.13.dist-info/WHEEL
ngsphy-1.0.13.dist-info/entry_points.txt
ngsphy-1.0.13.dist-info/metadata.json
ngsphy-1.0.13.dist-info/top_level.txt
