Metadata-Version: 2.0
Name: ngsphy
Version: 1.0.13
Summary: phylogenomic simulation of NGS data 
Home-page: https://github.com/merlyescalona/ngsphy
Author: Merly Escalona
Author-email: merlyescalona@uvigo.es
License: GNU/GPL v3
Download-URL: https://github.com/merlyescalona/ngsphy/blob/master/dist/ngsphy-1.0.13.tar.gz
Keywords: biology phylogenomics next-generation sequencing coverage targeted-sequencing
Platform: UNKNOWN
Classifier: Development Status :: 4 - Beta
Classifier: Intended Audience :: Education
Classifier: Intended Audience :: Science/Research
Classifier: Intended Audience :: Developers
Classifier: Topic :: Scientific/Engineering :: Bio-Informatics
Classifier: License :: OSI Approved :: GNU General Public License v3 (GPLv3)
Classifier: Programming Language :: Python :: 2.7
Requires-Python: ~=2.7
Requires-Dist: ConfigParser
Requires-Dist: argparse
Requires-Dist: datetime
Requires-Dist: dendropy
Requires-Dist: logging
Requires-Dist: multiprocessing
Requires-Dist: numpy
Requires-Dist: scipy
Requires-Dist: setuptools
